[
  {
    "callsign": "WA7JNJ",
    "track_notes": "In July 2021, road to this parking area was in good shape and I was able to drive a car.  This a short loop trail, and you can head to the summit either way.",
    "track_title": "Blue Mtn loop trail from parking",
    "posted_date": "2021-07-26 20:10:12",
    "points": [
      {
        "pt_index": "1",
        "latitude": "47.956510",
        "longitude": "-123.259900",
        "altitude": "1783.770",
        "distance": "0.000"
      },
      {
        "pt_index": "2",
        "latitude": "47.956480",
        "longitude": "-123.259880",
        "altitude": "1785.020",
        "distance": "3.657"
      },
      {
        "pt_index": "3",
        "latitude": "47.956450",
        "longitude": "-123.259860",
        "altitude": "1785.510",
        "distance": "3.657"
      },
      {
        "pt_index": "4",
        "latitude": "47.956420",
        "longitude": "-123.259850",
        "altitude": "1786.080",
        "distance": "3.422"
      },
      {
        "pt_index": "5",
        "latitude": "47.956410",
        "longitude": "-123.259810",
        "altitude": "1786.490",
        "distance": "3.183"
      },
      {
        "pt_index": "6",
        "latitude": "47.956370",
        "longitude": "-123.259790",
        "altitude": "1787.050",
        "distance": "4.696"
      },
      {
        "pt_index": "7",
        "latitude": "47.956340",
        "longitude": "-123.259780",
        "altitude": "1787.550",
        "distance": "3.422"
      },
      {
        "pt_index": "8",
        "latitude": "47.956300",
        "longitude": "-123.259790",
        "altitude": "1788.210",
        "distance": "4.515"
      },
      {
        "pt_index": "9",
        "latitude": "47.956270",
        "longitude": "-123.259800",
        "altitude": "1788.730",
        "distance": "3.422"
      },
      {
        "pt_index": "10",
        "latitude": "47.956240",
        "longitude": "-123.259810",
        "altitude": "1789.270",
        "distance": "3.422"
      },
      {
        "pt_index": "11",
        "latitude": "47.956200",
        "longitude": "-123.259830",
        "altitude": "1789.880",
        "distance": "4.696"
      },
      {
        "pt_index": "12",
        "latitude": "47.956170",
        "longitude": "-123.259830",
        "altitude": "1790.200",
        "distance": "3.340"
      },
      {
        "pt_index": "13",
        "latitude": "47.956140",
        "longitude": "-123.259860",
        "altitude": "1790.200",
        "distance": "4.019"
      },
      {
        "pt_index": "14",
        "latitude": "47.956120",
        "longitude": "-123.259890",
        "altitude": "1790.090",
        "distance": "3.156"
      },
      {
        "pt_index": "15",
        "latitude": "47.956100",
        "longitude": "-123.259930",
        "altitude": "1790.120",
        "distance": "3.721"
      },
      {
        "pt_index": "16",
        "latitude": "47.956110",
        "longitude": "-123.259980",
        "altitude": "1790.010",
        "distance": "3.890"
      },
      {
        "pt_index": "17",
        "latitude": "47.956100",
        "longitude": "-123.260010",
        "altitude": "1790.000",
        "distance": "2.498"
      },
      {
        "pt_index": "18",
        "latitude": "47.956050",
        "longitude": "-123.260010",
        "altitude": "1790.480",
        "distance": "5.566"
      },
      {
        "pt_index": "19",
        "latitude": "47.956000",
        "longitude": "-123.260010",
        "altitude": "1791.010",
        "distance": "5.566"
      },
      {
        "pt_index": "20",
        "latitude": "47.955970",
        "longitude": "-123.260010",
        "altitude": "1791.360",
        "distance": "3.340"
      },
      {
        "pt_index": "21",
        "latitude": "47.955940",
        "longitude": "-123.260020",
        "altitude": "1791.600",
        "distance": "3.422"
      },
      {
        "pt_index": "22",
        "latitude": "47.955910",
        "longitude": "-123.260030",
        "altitude": "1792.190",
        "distance": "3.422"
      },
      {
        "pt_index": "23",
        "latitude": "47.955880",
        "longitude": "-123.260060",
        "altitude": "1792.840",
        "distance": "4.019"
      },
      {
        "pt_index": "24",
        "latitude": "47.955850",
        "longitude": "-123.260070",
        "altitude": "1793.700",
        "distance": "3.422"
      },
      {
        "pt_index": "25",
        "latitude": "47.955820",
        "longitude": "-123.260080",
        "altitude": "1794.420",
        "distance": "3.422"
      },
      {
        "pt_index": "26",
        "latitude": "47.955790",
        "longitude": "-123.260100",
        "altitude": "1794.730",
        "distance": "3.657"
      },
      {
        "pt_index": "27",
        "latitude": "47.955770",
        "longitude": "-123.260120",
        "altitude": "1794.680",
        "distance": "2.680"
      },
      {
        "pt_index": "28",
        "latitude": "47.955740",
        "longitude": "-123.260140",
        "altitude": "1794.990",
        "distance": "3.657"
      },
      {
        "pt_index": "29",
        "latitude": "47.955720",
        "longitude": "-123.260160",
        "altitude": "1794.990",
        "distance": "2.680"
      },
      {
        "pt_index": "30",
        "latitude": "47.955690",
        "longitude": "-123.260180",
        "altitude": "1795.210",
        "distance": "3.657"
      },
      {
        "pt_index": "31",
        "latitude": "47.955660",
        "longitude": "-123.260200",
        "altitude": "1795.400",
        "distance": "3.657"
      },
      {
        "pt_index": "32",
        "latitude": "47.955630",
        "longitude": "-123.260220",
        "altitude": "1795.640",
        "distance": "3.657"
      },
      {
        "pt_index": "33",
        "latitude": "47.955610",
        "longitude": "-123.260240",
        "altitude": "1795.640",
        "distance": "2.680"
      },
      {
        "pt_index": "34",
        "latitude": "47.955570",
        "longitude": "-123.260250",
        "altitude": "1796.290",
        "distance": "4.515"
      },
      {
        "pt_index": "35",
        "latitude": "47.955550",
        "longitude": "-123.260260",
        "altitude": "1796.500",
        "distance": "2.348"
      },
      {
        "pt_index": "36",
        "latitude": "47.955520",
        "longitude": "-123.260270",
        "altitude": "1796.940",
        "distance": "3.422"
      },
      {
        "pt_index": "37",
        "latitude": "47.955490",
        "longitude": "-123.260280",
        "altitude": "1797.360",
        "distance": "3.422"
      },
      {
        "pt_index": "38",
        "latitude": "47.955460",
        "longitude": "-123.260270",
        "altitude": "1798.230",
        "distance": "3.422"
      },
      {
        "pt_index": "39",
        "latitude": "47.955420",
        "longitude": "-123.260280",
        "altitude": "1798.880",
        "distance": "4.515"
      },
      {
        "pt_index": "40",
        "latitude": "47.955420",
        "longitude": "-123.260320",
        "altitude": "1798.020",
        "distance": "2.982"
      },
      {
        "pt_index": "41",
        "latitude": "47.955390",
        "longitude": "-123.260310",
        "altitude": "1798.880",
        "distance": "3.422"
      },
      {
        "pt_index": "42",
        "latitude": "47.955360",
        "longitude": "-123.260300",
        "altitude": "1799.720",
        "distance": "3.422"
      },
      {
        "pt_index": "43",
        "latitude": "47.955320",
        "longitude": "-123.260310",
        "altitude": "1800.200",
        "distance": "4.515"
      },
      {
        "pt_index": "44",
        "latitude": "47.955290",
        "longitude": "-123.260310",
        "altitude": "1800.740",
        "distance": "3.340"
      },
      {
        "pt_index": "45",
        "latitude": "47.955250",
        "longitude": "-123.260320",
        "altitude": "1801.230",
        "distance": "4.515"
      },
      {
        "pt_index": "46",
        "latitude": "47.955220",
        "longitude": "-123.260310",
        "altitude": "1802.200",
        "distance": "3.422"
      },
      {
        "pt_index": "47",
        "latitude": "47.955180",
        "longitude": "-123.260300",
        "altitude": "1803.410",
        "distance": "4.515"
      },
      {
        "pt_index": "48",
        "latitude": "47.955150",
        "longitude": "-123.260300",
        "altitude": "1804.130",
        "distance": "3.340"
      },
      {
        "pt_index": "49",
        "latitude": "47.955110",
        "longitude": "-123.260280",
        "altitude": "1805.570",
        "distance": "4.696"
      },
      {
        "pt_index": "50",
        "latitude": "47.955080",
        "longitude": "-123.260270",
        "altitude": "1806.660",
        "distance": "3.422"
      },
      {
        "pt_index": "51",
        "latitude": "47.955050",
        "longitude": "-123.260260",
        "altitude": "1807.960",
        "distance": "3.422"
      },
      {
        "pt_index": "52",
        "latitude": "47.955020",
        "longitude": "-123.260260",
        "altitude": "1808.930",
        "distance": "3.340"
      },
      {
        "pt_index": "53",
        "latitude": "47.954990",
        "longitude": "-123.260250",
        "altitude": "1810.010",
        "distance": "3.422"
      },
      {
        "pt_index": "54",
        "latitude": "47.954960",
        "longitude": "-123.260240",
        "altitude": "1810.660",
        "distance": "3.422"
      },
      {
        "pt_index": "55",
        "latitude": "47.954940",
        "longitude": "-123.260200",
        "altitude": "1812.170",
        "distance": "3.722"
      },
      {
        "pt_index": "56",
        "latitude": "47.954910",
        "longitude": "-123.260180",
        "altitude": "1813.090",
        "distance": "3.657"
      },
      {
        "pt_index": "57",
        "latitude": "47.954880",
        "longitude": "-123.260170",
        "altitude": "1813.330",
        "distance": "3.422"
      },
      {
        "pt_index": "58",
        "latitude": "47.954850",
        "longitude": "-123.260170",
        "altitude": "1813.330",
        "distance": "3.340"
      },
      {
        "pt_index": "59",
        "latitude": "47.954810",
        "longitude": "-123.260150",
        "altitude": "1813.760",
        "distance": "4.696"
      },
      {
        "pt_index": "60",
        "latitude": "47.954780",
        "longitude": "-123.260140",
        "altitude": "1813.980",
        "distance": "3.422"
      },
      {
        "pt_index": "61",
        "latitude": "47.954750",
        "longitude": "-123.260120",
        "altitude": "1814.410",
        "distance": "3.657"
      },
      {
        "pt_index": "62",
        "latitude": "47.954720",
        "longitude": "-123.260130",
        "altitude": "1814.210",
        "distance": "3.422"
      },
      {
        "pt_index": "63",
        "latitude": "47.954700",
        "longitude": "-123.260110",
        "altitude": "1814.820",
        "distance": "2.680"
      },
      {
        "pt_index": "64",
        "latitude": "47.954660",
        "longitude": "-123.260090",
        "altitude": "1815.730",
        "distance": "4.696"
      },
      {
        "pt_index": "65",
        "latitude": "47.954630",
        "longitude": "-123.260040",
        "altitude": "1817.130",
        "distance": "5.005"
      },
      {
        "pt_index": "66",
        "latitude": "47.954610",
        "longitude": "-123.260020",
        "altitude": "1817.780",
        "distance": "2.680"
      },
      {
        "pt_index": "67",
        "latitude": "47.954590",
        "longitude": "-123.259990",
        "altitude": "1818.640",
        "distance": "3.156"
      },
      {
        "pt_index": "68",
        "latitude": "47.954570",
        "longitude": "-123.259950",
        "altitude": "1819.720",
        "distance": "3.722"
      },
      {
        "pt_index": "69",
        "latitude": "47.954550",
        "longitude": "-123.259920",
        "altitude": "1820.590",
        "distance": "3.156"
      },
      {
        "pt_index": "70",
        "latitude": "47.954530",
        "longitude": "-123.259890",
        "altitude": "1821.360",
        "distance": "3.156"
      },
      {
        "pt_index": "71",
        "latitude": "47.954500",
        "longitude": "-123.259870",
        "altitude": "1821.650",
        "distance": "3.657"
      },
      {
        "pt_index": "72",
        "latitude": "47.954480",
        "longitude": "-123.259850",
        "altitude": "1821.860",
        "distance": "2.680"
      },
      {
        "pt_index": "73",
        "latitude": "47.954450",
        "longitude": "-123.259820",
        "altitude": "1822.000",
        "distance": "4.019"
      },
      {
        "pt_index": "74",
        "latitude": "47.954420",
        "longitude": "-123.259790",
        "altitude": "1822.270",
        "distance": "4.019"
      },
      {
        "pt_index": "75",
        "latitude": "47.954380",
        "longitude": "-123.259810",
        "altitude": "1821.410",
        "distance": "4.696"
      },
      {
        "pt_index": "76",
        "latitude": "47.954350",
        "longitude": "-123.259840",
        "altitude": "1820.710",
        "distance": "4.019"
      },
      {
        "pt_index": "77",
        "latitude": "47.954320",
        "longitude": "-123.259820",
        "altitude": "1820.600",
        "distance": "3.657"
      },
      {
        "pt_index": "78",
        "latitude": "47.954320",
        "longitude": "-123.259770",
        "altitude": "1821.460",
        "distance": "3.728"
      },
      {
        "pt_index": "79",
        "latitude": "47.954300",
        "longitude": "-123.259730",
        "altitude": "1821.760",
        "distance": "3.722"
      },
      {
        "pt_index": "80",
        "latitude": "47.954290",
        "longitude": "-123.259680",
        "altitude": "1822.120",
        "distance": "3.890"
      },
      {
        "pt_index": "81",
        "latitude": "47.954270",
        "longitude": "-123.259650",
        "altitude": "1822.010",
        "distance": "3.156"
      },
      {
        "pt_index": "82",
        "latitude": "47.954250",
        "longitude": "-123.259610",
        "altitude": "1822.110",
        "distance": "3.722"
      },
      {
        "pt_index": "83",
        "latitude": "47.954240",
        "longitude": "-123.259550",
        "altitude": "1822.650",
        "distance": "4.610"
      },
      {
        "pt_index": "84",
        "latitude": "47.954240",
        "longitude": "-123.259510",
        "altitude": "1823.020",
        "distance": "2.982"
      },
      {
        "pt_index": "85",
        "latitude": "47.954240",
        "longitude": "-123.259470",
        "altitude": "1823.370",
        "distance": "2.982"
      },
      {
        "pt_index": "86",
        "latitude": "47.954230",
        "longitude": "-123.259420",
        "altitude": "1823.370",
        "distance": "3.890"
      },
      {
        "pt_index": "87",
        "latitude": "47.954260",
        "longitude": "-123.259380",
        "altitude": "1824.010",
        "distance": "4.477"
      },
      {
        "pt_index": "88",
        "latitude": "47.954290",
        "longitude": "-123.259370",
        "altitude": "1824.330",
        "distance": "3.422"
      },
      {
        "pt_index": "89",
        "latitude": "47.954320",
        "longitude": "-123.259370",
        "altitude": "1824.660",
        "distance": "3.340"
      },
      {
        "pt_index": "90",
        "latitude": "47.954350",
        "longitude": "-123.259360",
        "altitude": "1824.980",
        "distance": "3.422"
      },
      {
        "pt_index": "91",
        "latitude": "47.954380",
        "longitude": "-123.259370",
        "altitude": "1825.910",
        "distance": "3.422"
      },
      {
        "pt_index": "92",
        "latitude": "47.954410",
        "longitude": "-123.259390",
        "altitude": "1826.880",
        "distance": "3.657"
      },
      {
        "pt_index": "93",
        "latitude": "47.954440",
        "longitude": "-123.259400",
        "altitude": "1827.860",
        "distance": "3.422"
      },
      {
        "pt_index": "94",
        "latitude": "47.954470",
        "longitude": "-123.259410",
        "altitude": "1828.550",
        "distance": "3.422"
      },
      {
        "pt_index": "95",
        "latitude": "47.954500",
        "longitude": "-123.259430",
        "altitude": "1829.200",
        "distance": "3.657"
      },
      {
        "pt_index": "96",
        "latitude": "47.954530",
        "longitude": "-123.259460",
        "altitude": "1829.520",
        "distance": "4.019"
      },
      {
        "pt_index": "97",
        "latitude": "47.954560",
        "longitude": "-123.259480",
        "altitude": "1829.580",
        "distance": "3.657"
      },
      {
        "pt_index": "98",
        "latitude": "47.954590",
        "longitude": "-123.259490",
        "altitude": "1829.870",
        "distance": "3.422"
      },
      {
        "pt_index": "99",
        "latitude": "47.954620",
        "longitude": "-123.259520",
        "altitude": "1830.000",
        "distance": "4.019"
      },
      {
        "pt_index": "100",
        "latitude": "47.954650",
        "longitude": "-123.259550",
        "altitude": "1830.050",
        "distance": "4.019"
      },
      {
        "pt_index": "101",
        "latitude": "47.954680",
        "longitude": "-123.259560",
        "altitude": "1830.160",
        "distance": "3.422"
      },
      {
        "pt_index": "102",
        "latitude": "47.954710",
        "longitude": "-123.259570",
        "altitude": "1830.200",
        "distance": "3.422"
      },
      {
        "pt_index": "103",
        "latitude": "47.954730",
        "longitude": "-123.259580",
        "altitude": "1830.110",
        "distance": "2.348"
      },
      {
        "pt_index": "104",
        "latitude": "47.954760",
        "longitude": "-123.259590",
        "altitude": "1830.090",
        "distance": "3.422"
      },
      {
        "pt_index": "105",
        "latitude": "47.954790",
        "longitude": "-123.259600",
        "altitude": "1830.140",
        "distance": "3.422"
      },
      {
        "pt_index": "106",
        "latitude": "47.954810",
        "longitude": "-123.259630",
        "altitude": "1829.930",
        "distance": "3.156"
      },
      {
        "pt_index": "107",
        "latitude": "47.954840",
        "longitude": "-123.259610",
        "altitude": "1829.880",
        "distance": "3.657"
      },
      {
        "pt_index": "108",
        "latitude": "47.954870",
        "longitude": "-123.259580",
        "altitude": "1829.620",
        "distance": "4.019"
      },
      {
        "pt_index": "109",
        "latitude": "47.954880",
        "longitude": "-123.259540",
        "altitude": "1829.580",
        "distance": "3.183"
      },
      {
        "pt_index": "110",
        "latitude": "47.954910",
        "longitude": "-123.259550",
        "altitude": "1828.890",
        "distance": "3.422"
      },
      {
        "pt_index": "111",
        "latitude": "47.954940",
        "longitude": "-123.259560",
        "altitude": "1827.680",
        "distance": "3.422"
      },
      {
        "pt_index": "112",
        "latitude": "47.954970",
        "longitude": "-123.259560",
        "altitude": "1826.460",
        "distance": "3.340"
      },
      {
        "pt_index": "113",
        "latitude": "47.955040",
        "longitude": "-123.259580",
        "altitude": "1824.400",
        "distance": "7.934"
      },
      {
        "pt_index": "114",
        "latitude": "47.955060",
        "longitude": "-123.259620",
        "altitude": "1824.020",
        "distance": "3.722"
      },
      {
        "pt_index": "115",
        "latitude": "47.955090",
        "longitude": "-123.259620",
        "altitude": "1823.080",
        "distance": "3.340"
      },
      {
        "pt_index": "116",
        "latitude": "47.955110",
        "longitude": "-123.259610",
        "altitude": "1822.920",
        "distance": "2.348"
      },
      {
        "pt_index": "117",
        "latitude": "47.955150",
        "longitude": "-123.259610",
        "altitude": "1822.740",
        "distance": "4.453"
      },
      {
        "pt_index": "118",
        "latitude": "47.955180",
        "longitude": "-123.259610",
        "altitude": "1822.600",
        "distance": "3.340"
      },
      {
        "pt_index": "119",
        "latitude": "47.955210",
        "longitude": "-123.259620",
        "altitude": "1822.280",
        "distance": "3.422"
      },
      {
        "pt_index": "120",
        "latitude": "47.955240",
        "longitude": "-123.259620",
        "altitude": "1821.670",
        "distance": "3.340"
      },
      {
        "pt_index": "121",
        "latitude": "47.955270",
        "longitude": "-123.259620",
        "altitude": "1821.060",
        "distance": "3.340"
      },
      {
        "pt_index": "122",
        "latitude": "47.955300",
        "longitude": "-123.259640",
        "altitude": "1820.140",
        "distance": "3.657"
      },
      {
        "pt_index": "123",
        "latitude": "47.955330",
        "longitude": "-123.259650",
        "altitude": "1818.960",
        "distance": "3.422"
      },
      {
        "pt_index": "124",
        "latitude": "47.955360",
        "longitude": "-123.259640",
        "altitude": "1818.120",
        "distance": "3.422"
      },
      {
        "pt_index": "125",
        "latitude": "47.955390",
        "longitude": "-123.259630",
        "altitude": "1817.140",
        "distance": "3.422"
      },
      {
        "pt_index": "126",
        "latitude": "47.955420",
        "longitude": "-123.259630",
        "altitude": "1815.850",
        "distance": "3.340"
      },
      {
        "pt_index": "127",
        "latitude": "47.955450",
        "longitude": "-123.259610",
        "altitude": "1814.950",
        "distance": "3.657"
      },
      {
        "pt_index": "128",
        "latitude": "47.955460",
        "longitude": "-123.259570",
        "altitude": "1815.400",
        "distance": "3.183"
      },
      {
        "pt_index": "129",
        "latitude": "47.955480",
        "longitude": "-123.259540",
        "altitude": "1814.840",
        "distance": "3.156"
      },
      {
        "pt_index": "130",
        "latitude": "47.955510",
        "longitude": "-123.259530",
        "altitude": "1812.950",
        "distance": "3.422"
      },
      {
        "pt_index": "131",
        "latitude": "47.955540",
        "longitude": "-123.259530",
        "altitude": "1811.060",
        "distance": "3.340"
      },
      {
        "pt_index": "132",
        "latitude": "47.955570",
        "longitude": "-123.259520",
        "altitude": "1809.720",
        "distance": "3.422"
      },
      {
        "pt_index": "133",
        "latitude": "47.955600",
        "longitude": "-123.259500",
        "altitude": "1808.960",
        "distance": "3.657"
      },
      {
        "pt_index": "134",
        "latitude": "47.955630",
        "longitude": "-123.259490",
        "altitude": "1808.100",
        "distance": "3.422"
      },
      {
        "pt_index": "135",
        "latitude": "47.955660",
        "longitude": "-123.259460",
        "altitude": "1807.580",
        "distance": "4.019"
      },
      {
        "pt_index": "136",
        "latitude": "47.955640",
        "longitude": "-123.259420",
        "altitude": "1808.480",
        "distance": "3.721"
      },
      {
        "pt_index": "137",
        "latitude": "47.955680",
        "longitude": "-123.259420",
        "altitude": "1807.580",
        "distance": "4.453"
      },
      {
        "pt_index": "138",
        "latitude": "47.955710",
        "longitude": "-123.259410",
        "altitude": "1807.040",
        "distance": "3.422"
      },
      {
        "pt_index": "139",
        "latitude": "47.955740",
        "longitude": "-123.259410",
        "altitude": "1806.390",
        "distance": "3.340"
      },
      {
        "pt_index": "140",
        "latitude": "47.955770",
        "longitude": "-123.259380",
        "altitude": "1805.970",
        "distance": "4.019"
      },
      {
        "pt_index": "141",
        "latitude": "47.955780",
        "longitude": "-123.259340",
        "altitude": "1806.280",
        "distance": "3.183"
      },
      {
        "pt_index": "142",
        "latitude": "47.955790",
        "longitude": "-123.259300",
        "altitude": "1806.500",
        "distance": "3.183"
      },
      {
        "pt_index": "143",
        "latitude": "47.955810",
        "longitude": "-123.259270",
        "altitude": "1806.390",
        "distance": "3.156"
      },
      {
        "pt_index": "144",
        "latitude": "47.955860",
        "longitude": "-123.259260",
        "altitude": "1805.410",
        "distance": "5.616"
      },
      {
        "pt_index": "145",
        "latitude": "47.955890",
        "longitude": "-123.259260",
        "altitude": "1804.760",
        "distance": "3.340"
      },
      {
        "pt_index": "146",
        "latitude": "47.955910",
        "longitude": "-123.259210",
        "altitude": "1804.880",
        "distance": "4.342"
      },
      {
        "pt_index": "147",
        "latitude": "47.955930",
        "longitude": "-123.259160",
        "altitude": "1805.010",
        "distance": "4.342"
      },
      {
        "pt_index": "148",
        "latitude": "47.955940",
        "longitude": "-123.259120",
        "altitude": "1805.550",
        "distance": "3.183"
      },
      {
        "pt_index": "149",
        "latitude": "47.955940",
        "longitude": "-123.259070",
        "altitude": "1806.550",
        "distance": "3.728"
      },
      {
        "pt_index": "150",
        "latitude": "47.955960",
        "longitude": "-123.259030",
        "altitude": "1806.070",
        "distance": "3.721"
      },
      {
        "pt_index": "151",
        "latitude": "47.955990",
        "longitude": "-123.259020",
        "altitude": "1805.330",
        "distance": "3.422"
      },
      {
        "pt_index": "152",
        "latitude": "47.956030",
        "longitude": "-123.259020",
        "altitude": "1804.020",
        "distance": "4.453"
      },
      {
        "pt_index": "153",
        "latitude": "47.956050",
        "longitude": "-123.259000",
        "altitude": "1803.170",
        "distance": "2.680"
      },
      {
        "pt_index": "154",
        "latitude": "47.956060",
        "longitude": "-123.258950",
        "altitude": "1802.760",
        "distance": "3.890"
      },
      {
        "pt_index": "155",
        "latitude": "47.956060",
        "longitude": "-123.258910",
        "altitude": "1802.760",
        "distance": "2.982"
      },
      {
        "pt_index": "156",
        "latitude": "47.956060",
        "longitude": "-123.258860",
        "altitude": "1802.590",
        "distance": "3.728"
      },
      {
        "pt_index": "157",
        "latitude": "47.956050",
        "longitude": "-123.258820",
        "altitude": "1802.810",
        "distance": "3.183"
      },
      {
        "pt_index": "158",
        "latitude": "47.956040",
        "longitude": "-123.258780",
        "altitude": "1802.580",
        "distance": "3.183"
      },
      {
        "pt_index": "159",
        "latitude": "47.956050",
        "longitude": "-123.258740",
        "altitude": "1801.020",
        "distance": "3.183"
      },
      {
        "pt_index": "160",
        "latitude": "47.956070",
        "longitude": "-123.258720",
        "altitude": "1799.760",
        "distance": "2.680"
      },
      {
        "pt_index": "161",
        "latitude": "47.956100",
        "longitude": "-123.258710",
        "altitude": "1798.500",
        "distance": "3.422"
      },
      {
        "pt_index": "162",
        "latitude": "47.956140",
        "longitude": "-123.258700",
        "altitude": "1796.370",
        "distance": "4.515"
      },
      {
        "pt_index": "163",
        "latitude": "47.956170",
        "longitude": "-123.258720",
        "altitude": "1795.060",
        "distance": "3.657"
      },
      {
        "pt_index": "164",
        "latitude": "47.956180",
        "longitude": "-123.258760",
        "altitude": "1795.040",
        "distance": "3.183"
      },
      {
        "pt_index": "165",
        "latitude": "47.956200",
        "longitude": "-123.258800",
        "altitude": "1794.280",
        "distance": "3.721"
      },
      {
        "pt_index": "166",
        "latitude": "47.956220",
        "longitude": "-123.258820",
        "altitude": "1793.380",
        "distance": "2.680"
      },
      {
        "pt_index": "167",
        "latitude": "47.956250",
        "longitude": "-123.258870",
        "altitude": "1792.300",
        "distance": "5.005"
      },
      {
        "pt_index": "168",
        "latitude": "47.956270",
        "longitude": "-123.258910",
        "altitude": "1791.580",
        "distance": "3.721"
      },
      {
        "pt_index": "169",
        "latitude": "47.956260",
        "longitude": "-123.258950",
        "altitude": "1792.360",
        "distance": "3.183"
      },
      {
        "pt_index": "170",
        "latitude": "47.956280",
        "longitude": "-123.258990",
        "altitude": "1791.720",
        "distance": "3.721"
      },
      {
        "pt_index": "171",
        "latitude": "47.956320",
        "longitude": "-123.259000",
        "altitude": "1789.260",
        "distance": "4.515"
      },
      {
        "pt_index": "172",
        "latitude": "47.956350",
        "longitude": "-123.259010",
        "altitude": "1787.120",
        "distance": "3.422"
      },
      {
        "pt_index": "173",
        "latitude": "47.956380",
        "longitude": "-123.259040",
        "altitude": "1785.240",
        "distance": "4.019"
      },
      {
        "pt_index": "174",
        "latitude": "47.956390",
        "longitude": "-123.259090",
        "altitude": "1784.890",
        "distance": "3.890"
      },
      {
        "pt_index": "175",
        "latitude": "47.956380",
        "longitude": "-123.259140",
        "altitude": "1785.580",
        "distance": "3.890"
      },
      {
        "pt_index": "176",
        "latitude": "47.956400",
        "longitude": "-123.259170",
        "altitude": "1784.040",
        "distance": "3.156"
      },
      {
        "pt_index": "177",
        "latitude": "47.956410",
        "longitude": "-123.259220",
        "altitude": "1783.310",
        "distance": "3.890"
      },
      {
        "pt_index": "178",
        "latitude": "47.956380",
        "longitude": "-123.259260",
        "altitude": "1785.580",
        "distance": "4.477"
      },
      {
        "pt_index": "179",
        "latitude": "47.956360",
        "longitude": "-123.259290",
        "altitude": "1786.770",
        "distance": "3.156"
      },
      {
        "pt_index": "180",
        "latitude": "47.956330",
        "longitude": "-123.259330",
        "altitude": "1788.330",
        "distance": "4.477"
      },
      {
        "pt_index": "181",
        "latitude": "47.956310",
        "longitude": "-123.259360",
        "altitude": "1789.260",
        "distance": "3.156"
      },
      {
        "pt_index": "182",
        "latitude": "47.956300",
        "longitude": "-123.259410",
        "altitude": "1789.800",
        "distance": "3.890"
      },
      {
        "pt_index": "183",
        "latitude": "47.956300",
        "longitude": "-123.259460",
        "altitude": "1789.810",
        "distance": "3.728"
      },
      {
        "pt_index": "184",
        "latitude": "47.956310",
        "longitude": "-123.259500",
        "altitude": "1789.350",
        "distance": "3.183"
      },
      {
        "pt_index": "185",
        "latitude": "47.956330",
        "longitude": "-123.259530",
        "altitude": "1788.520",
        "distance": "3.156"
      },
      {
        "pt_index": "186",
        "latitude": "47.956330",
        "longitude": "-123.259580",
        "altitude": "1788.250",
        "distance": "3.728"
      },
      {
        "pt_index": "187",
        "latitude": "47.956340",
        "longitude": "-123.259630",
        "altitude": "1787.580",
        "distance": "3.890"
      },
      {
        "pt_index": "188",
        "latitude": "47.956340",
        "longitude": "-123.259670",
        "altitude": "1787.580",
        "distance": "2.982"
      },
      {
        "pt_index": "189",
        "latitude": "47.956350",
        "longitude": "-123.259720",
        "altitude": "1787.260",
        "distance": "3.890"
      },
      {
        "pt_index": "190",
        "latitude": "47.956360",
        "longitude": "-123.259760",
        "altitude": "1787.090",
        "distance": "3.183"
      },
      {
        "pt_index": "191",
        "latitude": "47.956390",
        "longitude": "-123.259790",
        "altitude": "1786.710",
        "distance": "4.019"
      },
      {
        "pt_index": "192",
        "latitude": "47.956410",
        "longitude": "-123.259820",
        "altitude": "1786.500",
        "distance": "3.156"
      },
      {
        "pt_index": "193",
        "latitude": "47.956430",
        "longitude": "-123.259850",
        "altitude": "1785.900",
        "distance": "3.156"
      },
      {
        "pt_index": "194",
        "latitude": "47.956450",
        "longitude": "-123.259880",
        "altitude": "1785.440",
        "distance": "3.156"
      },
      {
        "pt_index": "195",
        "latitude": "47.956460",
        "longitude": "-123.259930",
        "altitude": "1785.230",
        "distance": "3.890"
      },
      {
        "pt_index": "196",
        "latitude": "47.956490",
        "longitude": "-123.259940",
        "altitude": "1784.630",
        "distance": "3.422"
      },
      {
        "pt_index": "197",
        "latitude": "47.956500",
        "longitude": "-123.259890",
        "altitude": "1784.200",
        "distance": "3.890"
      },
      {
        "pt_index": "198",
        "latitude": "47.956470",
        "longitude": "-123.259880",
        "altitude": "1785.160",
        "distance": "3.422"
      },
      {
        "pt_index": "199",
        "latitude": "47.956470",
        "longitude": "-123.259890",
        "altitude": "1785.150",
        "distance": "0.746"
      }
    ]
  }
]